README.md
code_census/__init__.py
code_census/alembic/README
code_census/alembic/env.py
code_census/alembic/script.py.mako
code_census/alembic/versions/cc7054b42c18_add_initial_tables.py
code_census/alembic.ini
code_census/cli.py
code_census/formatter.py
code_census/models.py
code_census/mypy_utils.py
code_census-0.0.16.dist-info/entry_points.txt
code_census-0.0.16.dist-info/LICENSE
code_census-0.0.16.dist-info/WHEEL
code_census-0.0.16.dist-info/METADATA
code_census-0.0.16.dist-info/RECORD
